simsplitchem/__init__.py
simsplitchem/simsplitchem.py
simsplitchem/samplers/__init__.py
simsplitchem/utils/__init__.py
test/__init__.py
test/test_simsplitchem.py
simsplitchem-0.0.0.dist-info/LICENSE
simsplitchem-0.0.0.dist-info/METADATA
simsplitchem-0.0.0.dist-info/WHEEL
simsplitchem-0.0.0.dist-info/top_level.txt
simsplitchem-0.0.0.dist-info/RECORD
